canopy_mcp/__init__.py
canopy_mcp/__main__.py
canopy_mcp/main.py
canopy_mcp/policy.py
canopy_mcp/secret_resolver.py
canopy_mcp-0.6.0.dist-info/licenses/LICENSE.md
canopy_mcp-0.6.0.dist-info/METADATA
canopy_mcp-0.6.0.dist-info/WHEEL
canopy_mcp-0.6.0.dist-info/top_level.txt
canopy_mcp-0.6.0.dist-info/RECORD
