Metadata-Version: 2.4
Name: canopy_mcp
Version: 0.6.0
Summary: An MCP proxy server that allows you to write and enforce policies on MCP tool flows
Home-page: https://github.com/riskytrees/canopy
Author: Josiah Bruner
Author-email: RiskyTrees Labs <hello@riskytrees.com>
License: Canopy is available for personal use or non-profits. A license is needed for commercial use.
Project-URL: Homepage, https://riskytrees.com/canopymcp
Requires-Python: >=3.11
License-File: LICENSE.md
Requires-Dist: fastmcp
Requires-Dist: torch
Requires-Dist: transformers
Dynamic: license-file
